[
  {
    "id": 30060,
    "date": "18.02.2025",
    "article_url": "https://www.20min.ch/story/faktencheck-hiv-in-covid-impfstoff-schnipsel-aus-bbc-doku-missbraucht-103284087",
    "article_title": "HIV in Covid-Impfstoff? Schnipsel aus BBC-Doku missbraucht",
    "artefact_url": "https://archive.is/l8QGA",
    "factchecking_platform": 3,
    "original_platform": 16,
    "post_topic": 3,
    "user_generated_tags": [
      "HIV",
      "BBC",
      "World",
      "News"
    ],
    "keyword_coherence": 1,
    "source_actor": 1,
    "source_role": 99,
    "source_country": 99,
    "content_reference_country": 99,
    "content_creation_purpose": 22,
    "post_sentiment": 6,
    "fVar_artefact": 2,
    "visual_disinformation_category": 23,
    "visual_disinformation_topic": 31,
    "visual_coherence": 3,
    "visual_sentiment": 9,
    "auditive_specifications": 1,
    "visual_cut_tempo": 17.5,
    "relation_between_post_and_artefact": 1
  },
  {
    "id": 30061,
    "date": "11.02.2025",
    "article_url": "https://www.20min.ch/story/faktencheck-hiv-in-covid-impfstoff-schnipsel-aus-bbc-doku-missbraucht-103284087",
    "article_title": "HIV in Covid-Impfstoff? Schnipsel aus BBC-Doku missbraucht",
    "artefact_url": [
      "https://archive.is/27KlW"
    ],
    "factchecking_platform": 3,
    "original_platform": 20,
    "post_topic": 3,
    "user_generated_tags": [],
    "keyword_coherence": 9,
    "source_actor": 1,
    "source_role": 1,
    "source_country": 1,
    "content_reference_country": 99,
    "content_creation_purpose": 22,
    "post_sentiment": 3,
    "fVar_artefact": 2,
    "visual_disinformation_category": 23,
    "visual_disinformation_topic": 31,
    "visual_coherence": 3,
    "visual_sentiment": 9,
    "auditive_specifications": 1,
    "visual_cut_tempo": 17.5,
    "relation_between_post_and_artefact": 1
  },
  {
    "id": 30062,
    "date": "12.02.2025",
    "article_url": "https://www.20min.ch/story/faktencheck-hiv-in-covid-impfstoff-schnipsel-aus-bbc-doku-missbraucht-103284087",
    "article_title": "HIV in Covid-Impfstoff? Schnipsel aus BBC-Doku missbraucht",
    "artefact_url": [
      "https://archive.ph/VuEnJ"
    ],
    "factchecking_platform": 3,
    "original_platform": 13,
    "post_topic": 3,
    "user_generated_tags": [],
    "keyword_coherence": 9,
    "source_actor": 1,
    "source_role": 99,
    "source_country": 1,
    "content_reference_country": 99,
    "content_creation_purpose": 22,
    "post_sentiment": 3,
    "fVar_artefact": 2,
    "visual_disinformation_category": 23,
    "visual_disinformation_topic": 31,
    "visual_coherence": 3,
    "visual_sentiment": 9,
    "auditive_specifications": 1,
    "visual_cut_tempo": 17.5,
    "relation_between_post_and_artefact": 1
  },
  {
    "id": 30080,
    "date": "15.02.2025",
    "article_url": "https://www.20min.ch/story/fake-schnee-durch-chemtrails-faktencheck-klaert-auf-103283716",
    "article_title": "Erstaunlich, aber hier geht alles mit rechten Dingen zu",
    "artefact_url": "https://archive.is/cIAoD",
    "factchecking_platform": 3,
    "original_platform": 13,
    "post_topic": 3,
    "user_generated_tags": [],
    "keyword_coherence": 9,
    "source_actor": 1,
    "source_role": 99,
    "source_country": 1,
    "content_reference_country": 1,
    "content_creation_purpose": 21,
    "post_sentiment": 6,
    "fVar_artefact": 2,
    "visual_disinformation_category": 21,
    "visual_disinformation_topic": 32,
    "visual_coherence": 3,
    "visual_sentiment": 9,
    "auditive_specifications": 3,
    "visual_cut_tempo": 5.3,
    "relation_between_post_and_artefact": 1
  },
  {
    "id": 30081,
    "date": "15.02.2025",
    "article_url": "https://www.20min.ch/story/fake-schnee-durch-chemtrails-faktencheck-klaert-auf-103283716",
    "article_title": "Erstaunlich, aber hier geht alles mit rechten Dingen zu",
    "artefact_url": "https://archive.is/VgiN6",
    "factchecking_platform": 3,
    "original_platform": 13,
    "post_topic": 3,
    "user_generated_tags": [],
    "keyword_coherence": 9,
    "source_actor": 1,
    "source_role": 99,
    "source_country": 99,
    "content_reference_country": 99,
    "content_creation_purpose": 21,
    "post_sentiment": 6,
    "fVar_artefact": 2,
    "visual_disinformation_category": 21,
    "visual_disinformation_topic": 32,
    "visual_coherence": 3,
    "visual_sentiment": 3,
    "auditive_specifications": 3,
    "visual_cut_tempo": 1.8,
    "relation_between_post_and_artefact": 1
  },
  {
    "id": 30103,
    "date": "11.02.2025",
    "article_url": "https://www.20min.ch/story/faktencheck-trump-stinkefinger-bild-ist-kein-super-bowl-foto-103278617",
    "article_title": "Das Bild ist echt, aber nicht vom Superbowl 2025",
    "artefact_url": "https://archive.is/T8ISc",
    "factchecking_platform": 3,
    "original_platform": 16,
    "post_topic": 1,
    "user_generated_tags": [],
    "keyword_coherence": 9,
    "source_actor": 1,
    "source_role": 4,
    "source_country": 99,
    "content_reference_country": 2,
    "content_creation_purpose": 99,
    "post_sentiment": 9,
    "fVar_artefact": 1,
    "visual_disinformation_category": 11,
    "visual_disinformation_topic": 11,
    "visual_coherence": 9,
    "visual_sentiment": 4,
    "auditive_specifications": 2,
    "visual_cut_tempo": 0,
    "relation_between_post_and_artefact": 9
  },
  {
    "id": 30110,
    "date": "07.02.2025",
    "article_url": "https://www.20min.ch/story/antibock-in-der-schweizer-armee-video-als-fake-entlarvt-103278091",
    "article_title": "Erektionshemmer im Rekruten-Essen? Video nährt alte Gerüchte",
    "artefact_url": "https://archive.is/4sjwy",
    "factchecking_platform": 3,
    "original_platform": 12,
    "post_topic": 9,
    "user_generated_tags": [],
    "keyword_coherence": 9,
    "source_actor": 9,
    "source_role": 2,
    "source_country": 1,
    "content_reference_country": 1,
    "content_creation_purpose": 99,
    "post_sentiment": 9,
    "fVar_artefact": 2,
    "visual_disinformation_category": 23,
    "visual_disinformation_topic": 80,
    "visual_coherence": 9,
    "visual_sentiment": 1,
    "auditive_specifications": 2,
    "visual_cut_tempo": 5,
    "relation_between_post_and_artefact": 9
  },
  {
    "id": 30111,
    "date": "10.02.2025",
    "article_url": "https://www.20min.ch/story/antibock-in-der-schweizer-armee-video-als-fake-entlarvt-103278091",
    "article_title": "Erektionshemmer im Rekruten-Essen? Video nährt alte Gerüchte",
    "artefact_url": "https://archive.is/L7XJU",
    "factchecking_platform": 3,
    "original_platform": 30,
    "post_topic": 1,
    "user_generated_tags": [],
    "keyword_coherence": 9,
    "source_actor": 1,
    "source_role": 6,
    "source_country": 1,
    "content_reference_country": 1,
    "content_creation_purpose": 30,
    "post_sentiment": 1,
    "fVar_artefact": 1,
    "visual_disinformation_category": 13,
    "visual_disinformation_topic": 80,
    "visual_coherence": 4,
    "visual_sentiment": 9,
    "auditive_specifications": 9,
    "visual_cut_tempo": 0,
    "relation_between_post_and_artefact": 1
  },
  {
    "id": 30112,
    "date": "19.11.2014",
    "article_url": "https://www.20min.ch/story/antibock-in-der-schweizer-armee-video-als-fake-entlarvt-103278091",
    "article_title": "Erektionshemmer im Rekruten-Essen? Video nährt alte Gerüchte",
    "artefact_url": "https://archive.is/hn2BC",
    "factchecking_platform": 3,
    "original_platform": 13,
    "post_topic": 9,
    "user_generated_tags": [],
    "keyword_coherence": 9,
    "source_actor": 9,
    "source_role": 6,
    "source_country": 1,
    "content_reference_country": 1,
    "content_creation_purpose": 30,
    "post_sentiment": 1,
    "fVar_artefact": 1,
    "visual_disinformation_category": 13,
    "visual_disinformation_topic": 80,
    "visual_coherence": 4,
    "visual_sentiment": 9,
    "auditive_specifications": 9,
    "visual_cut_tempo": 0,
    "relation_between_post_and_artefact": 1
  },
  {
    "id": 30241,
    "date": "26.08.2024",
    "article_url": "https://www.20min.ch/story/anschlag-in-solingen-social-media-user-sehen-einen-skandal-den-gibt-es-aber-nicht-103175531",
    "article_title": "Wer ist Stefan? – ein Skandal, den es gar nicht gibt",
    "artefact_url": "https://archive.is/E66ew",
    "factchecking_platform": 3,
    "original_platform": 17,
    "post_topic": 8,
    "user_generated_tags": [],
    "keyword_coherence": 9,
    "source_actor": 1,
    "source_role": 99,
    "source_country": 99,
    "content_reference_country": 2,
    "content_creation_purpose": 22,
    "post_sentiment": 3,
    "fVar_artefact": 2,
    "visual_disinformation_category": 21,
    "visual_disinformation_topic": 22,
    "visual_coherence": 3,
    "visual_sentiment": 9,
    "auditive_specifications": 1,
    "visual_cut_tempo": 2.5,
    "relation_between_post_and_artefact": 1
  },
  {
    "id": 30251,
    "date": "14.08.2024",
    "article_url": "https://www.20min.ch/story/faktencheck-nein-mpox-hat-nichts-mit-den-covid-19-impfstoffen-zu-tun-103171678",
    "article_title": "Nein, Mpox hat nichts mit den Covid-19-Impfstoffen zu tun",
    "artefact_url": "https://www.facebook.com/photo?fbid=10160398979043412&set=p.10160398979043412",
    "factchecking_platform": 3,
    "original_platform": 13,
    "post_topic": 4,
    "user_generated_tags": [],
    "keyword_coherence": 9,
    "source_actor": 1,
    "source_role": 99,
    "source_country": 99,
    "content_reference_country": 99,
    "content_creation_purpose": 22,
    "post_sentiment": 3,
    "fVar_artefact": 1,
    "visual_disinformation_category": 15,
    "visual_disinformation_topic": 49,
    "visual_coherence": 3,
    "visual_sentiment": 3,
    "auditive_specifications": 9,
    "visual_cut_tempo": 0,
    "relation_between_post_and_artefact": 1
  },
  {
    "id": 30253,
    "date": "16.08.2024",
    "article_url": "https://www.20min.ch/story/faktencheck-nein-mpox-hat-nichts-mit-den-covid-19-impfstoffen-zu-tun-103171678",
    "article_title": "Nein, Mpox hat nichts mit den Covid-19-Impfstoffen zu tun",
    "artefact_url": "https://archive.is/wXdAO",
    "factchecking_platform": 3,
    "original_platform": 17,
    "post_topic": 4,
    "user_generated_tags": [],
    "keyword_coherence": 9,
    "source_actor": 1,
    "source_role": 1,
    "source_country": 2,
    "content_reference_country": 1,
    "content_creation_purpose": 22,
    "post_sentiment": 3,
    "fVar_artefact": 2,
    "visual_disinformation_category": 11,
    "visual_disinformation_topic": 49,
    "visual_coherence": 4,
    "visual_sentiment": 3,
    "auditive_specifications": 1,
    "visual_cut_tempo": 5.9,
    "relation_between_post_and_artefact": 1
  },
  {
    "id": 30254,
    "date": "16.08.2024",
    "article_url": "https://www.20min.ch/story/faktencheck-nein-mpox-hat-nichts-mit-den-covid-19-impfstoffen-zu-tun-103171678",
    "article_title": "Nein, Mpox hat nichts mit den Covid-19-Impfstoffen zu tun",
    "artefact_url": "https://archive.is/no1dQ",
    "factchecking_platform": 3,
    "original_platform": 17,
    "post_topic": 4,
    "user_generated_tags": [],
    "keyword_coherence": 9,
    "source_actor": 1,
    "source_role": 1,
    "source_country": 1,
    "content_reference_country": 1,
    "content_creation_purpose": 22,
    "post_sentiment": 1,
    "fVar_artefact": 2,
    "visual_disinformation_category": 11,
    "visual_disinformation_topic": 49,
    "visual_coherence": 4,
    "visual_sentiment": 3,
    "auditive_specifications": 1,
    "visual_cut_tempo": 5.9,
    "relation_between_post_and_artefact": 1
  },
  {
    "id": 30255,
    "date": "16.08.2024",
    "article_url": "https://www.20min.ch/story/faktencheck-nein-mpox-hat-nichts-mit-den-covid-19-impfstoffen-zu-tun-103171678",
    "article_title": "Nein, Mpox hat nichts mit den Covid-19-Impfstoffen zu tun",
    "artefact_url": "https://archive.is/UMbz2",
    "factchecking_platform": 3,
    "original_platform": 17,
    "post_topic": 4,
    "user_generated_tags": [
      "Affenpocken",
      "MPox",
      "Impfung"
    ],
    "keyword_coherence": 1,
    "source_actor": 1,
    "source_role": 1,
    "source_country": 1,
    "content_reference_country": 1,
    "content_creation_purpose": 22,
    "post_sentiment": 9,
    "fVar_artefact": 2,
    "visual_disinformation_category": 11,
    "visual_disinformation_topic": 49,
    "visual_coherence": 4,
    "visual_sentiment": 3,
    "auditive_specifications": 1,
    "visual_cut_tempo": 5.9,
    "relation_between_post_and_artefact": 1
  },
  {
    "id": 30256,
    "date": "16.08.2024",
    "article_url": "https://www.20min.ch/story/faktencheck-nein-mpox-hat-nichts-mit-den-covid-19-impfstoffen-zu-tun-103171678",
    "article_title": "Nein, Mpox hat nichts mit den Covid-19-Impfstoffen zu tun",
    "artefact_url": "https://archive.is/RtXhe",
    "factchecking_platform": 3,
    "original_platform": 17,
    "post_topic": 4,
    "user_generated_tags": [
      "Kongo",
      "Affentheater",
      "Pocken",
      "Biowaffenlabor",
      "Ebola",
      "Bergamo"
    ],
    "keyword_coherence": 1,
    "source_actor": 1,
    "source_role": 4,
    "source_country": 2,
    "content_reference_country": 1,
    "content_creation_purpose": 22,
    "post_sentiment": 3,
    "fVar_artefact": 2,
    "visual_disinformation_category": 11,
    "visual_disinformation_topic": 49,
    "visual_coherence": 4,
    "visual_sentiment": 3,
    "auditive_specifications": 1,
    "visual_cut_tempo": 0.3,
    "relation_between_post_and_artefact": 1
  },
  {
    "id": 30264,
    "date": "11.08.2024",
    "article_url": "https://www.20min.ch/story/olympia-2024-nein-eroeffnungsfeier-regisseur-wurde-nicht-von-blitz-getroffen-103167896",
    "article_title": "Gottes Rache an Olympia-Opening? Wohl eher russische Desinformation",
    "artefact_url": "https://archive.is/t17ps",
    "factchecking_platform": 3,
    "original_platform": 17,
    "post_topic": 6,
    "user_generated_tags": [],
    "keyword_coherence": 9,
    "source_actor": 1,
    "source_role": 1,
    "source_country": 4,
    "content_reference_country": 8,
    "content_creation_purpose": 22,
    "post_sentiment": 1,
    "fVar_artefact": 1,
    "visual_disinformation_category": 11,
    "visual_disinformation_topic": 21,
    "visual_coherence": 4,
    "visual_sentiment": 9,
    "auditive_specifications": 9,
    "visual_cut_tempo": 0,
    "relation_between_post_and_artefact": 1
  }
]